sqlinks/__init__.py
sqlinks/__main__.py
sqlinks/app/Objects.py
sqlinks/app/__init__.py
sqlinks/app/draw.py
sqlinks/app/helpers.py
sqlinks/app/open.py
sqlinks/app/parse.py
sqlinks/app/scan.py
sqlinks/app/templates/mermaid_template.md
tests/__init__.py
tests/test_draw.py
tests/test_parse.py
tests/test_populate.py
tests/test_scan.py
sqlinks-0.0.4.dist-info/LICENSE
sqlinks-0.0.4.dist-info/METADATA
sqlinks-0.0.4.dist-info/WHEEL
sqlinks-0.0.4.dist-info/top_level.txt
sqlinks-0.0.4.dist-info/RECORD
