Metadata-Version: 2.1
Name: sqlinks
Version: 0.0.4
Summary: Diagramming SQL data pipelines.
Author: Dominic Herriott
Author-email: dominicherriott@outlook.com
Keywords: python,documentation,sql
Classifier: Development Status :: 1 - Planning
Classifier: Intended Audience :: Developers
Classifier: Programming Language :: Python :: 3
Classifier: Operating System :: Unix
Classifier: Operating System :: MacOS :: MacOS X
Classifier: Operating System :: Microsoft :: Windows
License-File: LICENSE
Requires-Dist: sqlparse
Requires-Dist: sql-metadata
Requires-Dist: jinja2
